mcpo_simple_server/__init__.py
mcpo_simple_server/__main__.py
mcpo_simple_server/config.py
mcpo_simple_server/i18n.py
mcpo_simple_server/logger.py
mcpo_simple_server/main.py
mcpo_simple_server/metadata.py
mcpo_simple_server/requirements.txt
mcpo_simple_server/run.sh
mcpo_simple_server/template.py
mcpo_simple_server/assets/dist/css/tabler-flags.min.css
mcpo_simple_server/assets/dist/css/tabler-payments.min.css
mcpo_simple_server/assets/dist/css/tabler-vendors.min.css
mcpo_simple_server/assets/dist/css/tabler.min.css
mcpo_simple_server/assets/html/index.html
mcpo_simple_server/cli/cmd_kill.sh
mcpo_simple_server/locales/extract.sh
mcpo_simple_server/locales/init_lang.sh
mcpo_simple_server/locales/messages.pot
mcpo_simple_server/locales/update.sh
mcpo_simple_server/locales/fr_FR/LC_MESSAGES/messages.po
mcpo_simple_server/locales/pl_PL/LC_MESSAGES/messages.po
mcpo_simple_server/middleware/__init__.py
mcpo_simple_server/middleware/cors.py
mcpo_simple_server/middleware/dependencies.py
mcpo_simple_server/middleware/error_handler.py
mcpo_simple_server/middleware/language.py
mcpo_simple_server/middleware/logging.py
mcpo_simple_server/middleware/security.py
mcpo_simple_server/middleware/timing.py
mcpo_simple_server/routers/__init__.py
mcpo_simple_server/routers/admin/__init__.py
mcpo_simple_server/routers/admin/v1_delete_user.py
mcpo_simple_server/routers/admin/v1_post_tools_reload.py
mcpo_simple_server/routers/admin/v1_post_user.py
mcpo_simple_server/routers/mcp/v1_api_sse_docs.py
mcpo_simple_server/routers/mcpservers/__init__.py
mcpo_simple_server/routers/mcpservers/v1_delete_mcpserver.py
mcpo_simple_server/routers/mcpservers/v1_delete_mcpserver_env.py
mcpo_simple_server/routers/mcpservers/v1_delete_mcpserver_env_key.py
mcpo_simple_server/routers/mcpservers/v1_get_mcpserver_config.py
mcpo_simple_server/routers/mcpservers/v1_get_mcpserver_status.py
mcpo_simple_server/routers/mcpservers/v1_get_mcpservers_config.py
mcpo_simple_server-0.2.2.dist-info/METADATA
mcpo_simple_server-0.2.2.dist-info/WHEEL
mcpo_simple_server-0.2.2.dist-info/entry_points.txt
mcpo_simple_server-0.2.2.dist-info/top_level.txt
mcpo_simple_server-0.2.2.dist-info/RECORD
