Metadata-Version: 2.4
Name: mcpo-simple-server
Version: 0.2.2
Summary: Python-based LLM server that implements the Model Context Protocol (MCP)
Author-email: Artur Zdolinski <contact@nchekwa.com>
License: MIT
Project-URL: Homepage, https://getsimpletool.org
Project-URL: Bug Tracker, https://github.com/getsimpletool/mcpo-simple-server/issues
Classifier: Programming Language :: Python :: 3
Classifier: Programming Language :: Python :: 3.11
Classifier: License :: OSI Approved :: MIT License
Classifier: Operating System :: OS Independent
Requires-Python: >=3.11
Requires-Dist: fastapi>=0.115.14
Requires-Dist: uvicorn>=0.35.0
Requires-Dist: pydantic>=2.11.7
Requires-Dist: sse-starlette>=1.6.5
Requires-Dist: loguru>=0.7.3
Requires-Dist: python-dotenv>=1.0.0
Requires-Dist: uuid>=1.30
Requires-Dist: python-jose[cryptography]
Requires-Dist: passlib[bcrypt]>=1.7.4
Requires-Dist: aiofiles>=24.1.0
Requires-Dist: jinja2>=3.1.5
Requires-Dist: uv>=0.7.0
Requires-Dist: tinydb>=4.8.2
Requires-Dist: nosqlite>=0.0.3
Requires-Dist: dictdatabase>=2.5.1
Requires-Dist: mcp>=1.11.0
Requires-Dist: babel>=2.12.1
Dynamic: requires-dist
